setup.cfg
setup.py
gant/__init__.py
gant/main.py
gant.egg-info/PKG-INFO
gant.egg-info/SOURCES.txt
gant.egg-info/dependency_links.txt
gant.egg-info/entry_points.txt
gant.egg-info/requires.txt
gant.egg-info/top_level.txt
gant/utils/__init__.py
gant/utils/docker_helper.py
gant/utils/gant_ctx.py
gant/utils/gant_docker.py
gant/utils/ssh.py