Metadata-Version: 1.1
Name: gant
Version: 0.1.1
Summary: The Gluster development helper ant
Home-page: https://github.com/kshlm/gant
Author: Kaushal M
Author-email: kshlmster@gmail.com
License: BSD
Keywords: gluster docker utility development testing
Platform: UNKNOWN
Classifier: Development Status :: 3 - Alpha
Classifier: Topic :: Utilities
Classifier: License :: OSI Approved :: BSD License
Classifier: Environment :: Console
Classifier: Intended Audience :: Developers
Classifier: Operating System :: POSIX :: Linux
Classifier: Topic :: Utilities
Classifier: Programming Language :: Python :: 2
Classifier: Programming Language :: Python :: 2.6
Classifier: Programming Language :: Python :: 3
